khalorg/__init__.py
khalorg/__main__.py
khalorg/cli.py
khalorg/commands.py
khalorg/helpers.py
khalorg/logger.py
khalorg/paths.py
khalorg/rrule.py
khalorg/khal/args.py
khalorg/khal/calendar.py
khalorg/khal/checker.py
khalorg/khal/helpers.py
khalorg/org/agenda_items.py
khalorg/org/helpers.py
khalorg/static/__init__.py
khalorg/static/description_delete_command.txt
khalorg/static/description_edit_command.txt
khalorg/static/description_list_command.txt
khalorg/static/description_new_command.txt
khalorg/static/khal_format.txt
khalorg/static/khalorg_format.txt
khalorg-0.1.0.dist-info/LICENCE
khalorg-0.1.0.dist-info/METADATA
khalorg-0.1.0.dist-info/WHEEL
khalorg-0.1.0.dist-info/entry_points.txt
khalorg-0.1.0.dist-info/top_level.txt
khalorg-0.1.0.dist-info/RECORD
