Metadata-Version: 2.2
Name: khalorg
Version: 0.1.0
Summary: An interface between Org mode and Khal cli calendar.
Author: BartSte
License: MIT License
Keywords: khal,org mode,vdirsyncer,CalDav,agenda,emacs,neovim,orgmode-nvim
Classifier: Programming Language :: Python :: 3
Requires-Python: >=3.10
License-File: LICENCE
Requires-Dist: khal>=0.11
Requires-Dist: vdirsyncer
Requires-Dist: orgparse
Requires-Dist: icalendar<6.0
Provides-Extra: debug
Requires-Dist: ipdb; extra == "debug"
Requires-Dist: ipython; extra == "debug"
Provides-Extra: test
Requires-Dist: pytest; extra == "test"
Provides-Extra: build
Requires-Dist: build; extra == "build"
Requires-Dist: twine; extra == "build"
